sphinx_colorschemed_images/__init__.py
sphinx_colorschemed_images/exceptions.py
sphinx_colorschemed_images/extension.py
sphinx_colorschemed_images/translator.py
sphinx_colorschemed_images/static/sphinx-colorschemed-images.js
sphinx_colorschemed_images-0.3.0.dist-info/licenses/LICENSE
sphinx_colorschemed_images-0.3.0.dist-info/METADATA
sphinx_colorschemed_images-0.3.0.dist-info/WHEEL
sphinx_colorschemed_images-0.3.0.dist-info/top_level.txt
sphinx_colorschemed_images-0.3.0.dist-info/RECORD
