Metadata-Version: 2.4
Name: sphinx_colorschemed_images
Version: 0.3.0
Summary: A Sphinx extension to add support for colorschemed images.
Author-email: Daniela Rus Morales <danirus@eml.cc>
License: The MIT License (MIT)
Project-URL: Homepage, https://github.com/danirus/sphinx-colorschemed-images
Project-URL: Documentation, https://sphinx-colorschemed-images.readthedocs.io
Classifier: Development Status :: 4 - Beta
Classifier: Environment :: Web Environment
Classifier: Intended Audience :: Developers
Classifier: License :: OSI Approved :: MIT License
Classifier: Operating System :: OS Independent
Classifier: Programming Language :: Python
Classifier: Programming Language :: Python :: 3
Classifier: Programming Language :: Python :: 3.9
Classifier: Programming Language :: Python :: 3.10
Classifier: Programming Language :: Python :: 3.11
Classifier: Programming Language :: Python :: 3.12
Classifier: Programming Language :: Python :: 3.13
Classifier: Framework :: Sphinx
Classifier: Framework :: Sphinx :: Theme
Classifier: Topic :: Documentation
Classifier: Topic :: Software Development :: Documentation
Requires-Python: >=3.9
License-File: LICENSE
Requires-Dist: sphinx<10,>=6
Provides-Extra: dev
Requires-Dist: coverage<7.7,>=7.6.4; extra == "dev"
Requires-Dist: coverage-badge<1.2,>=1.1.2; extra == "dev"
Requires-Dist: lxml<5.4,>=5.3.0; extra == "dev"
Requires-Dist: pre-commit>=4.0.1; extra == "dev"
Requires-Dist: pytest<8.4,>=8.3.3; extra == "dev"
Requires-Dist: tox>=4.23.2; extra == "dev"
Requires-Dist: ruff>=0.7.0; extra == "dev"
Provides-Extra: docs
Requires-Dist: sphinx<10,>=6; extra == "docs"
Requires-Dist: myst-parser<5.1,>=5.0.0; extra == "docs"
Requires-Dist: sphinx-design<0.7,>=0.6.1; extra == "docs"
Requires-Dist: sphinx-colorschemed-images>=0.2.2; extra == "docs"
Requires-Dist: sphinx_copybutton<1.0.0,>=0.5.2; extra == "docs"
Requires-Dist: sphinx-nefertiti; extra == "docs"
Dynamic: license-file
